MANIFEST.in
setup.py
jds_write/__init__.py
jds_write/process.py
jds_write/text.py
jds_write.egg-info/PKG-INFO
jds_write.egg-info/SOURCES.txt
jds_write.egg-info/dependency_links.txt
jds_write.egg-info/not-zip-safe
jds_write.egg-info/requires.txt
jds_write.egg-info/top_level.txt