Metadata-Version: 1.0
Name: jds-write
Version: 0.11
Summary: The funniest joke in the world
Home-page: http://github.com/despiegj/jds_write
Author: Jan De Spiegeleer
Author-email: jds@riskconcile.com
License: MIT
Platform: UNKNOWN
